.gitignore
LICENSE.txt
NOTES.txt
README.rst
setup.py
lib/clahe/.gitignore
lib/clahe/__init__.py
lib/clahe/_clahe.py
lib/clahe/_clahe_impl.c
lib/clahe/_clahe_impl.pyx
lib/clahe/_version.py
lib/clahe.egg-info/PKG-INFO
lib/clahe.egg-info/SOURCES.txt
lib/clahe.egg-info/dependency_links.txt
lib/clahe.egg-info/requires.txt
lib/clahe.egg-info/top_level.txt
tests/__init__.py
tests/test_clahe.py