Metadata-Version: 1.2
Name: clahe
Version: 0.1
Summary: Exact contrast-limited adaptive histogram equalization
Home-page: https://github.com/anntzer/clahe
Author: Antony Lee
License: MIT
Platform: UNKNOWN
Classifier: Development Status :: 4 - Beta
Classifier: License :: OSI Approved :: MIT License
Classifier: Programming Language :: Python :: 3
Requires-Python: >=3
